{
  "project_info": {
    "project_number": "448410438196",
    "firebase_url": "https://mapslauncher.firebaseio.com",
    "project_id": "mapslauncher",
    "storage_bucket": "mapslauncher.appspot.com"
  },
  "client": [
    {
      "client_info": {
        "mobilesdk_app_id": "1:448410438196:android:d8abc66f8842aa88",
        "android_client_info": {
          "package_name": "com.example.onkar.mapslauncher"
        }
      },
      "oauth_client": [
        {
          "client_id": "448410438196-roqviubju4ejlrmnr4fcdkhga8al5rlp.apps.googleusercontent.com",
          "client_type": 1,
          "android_info": {
            "package_name": "com.example.onkar.mapslauncher",
            "certificate_hash": "43974289c34fd910862897601fa5d5a3ab04955f"
          }
        },
        {
          "client_id": "448410438196-4o6upunfjjk0qmkg4p5urci9jr5llk4l.apps.googleusercontent.com",
          "client_type": 3
        }
      ],
      "api_key": [
        {
          "current_key": "AIzaSyDblpEo2rGp-DG2beT4-htfd-veqXNT-Ew"
        }
      ],
      "services": {
        "analytics_service": {
          "status": 1
        },
        "appinvite_service": {
          "status": 2,
          "other_platform_oauth_client": [
            {
              "client_id": "448410438196-4o6upunfjjk0qmkg4p5urci9jr5llk4l.apps.googleusercontent.com",
              "client_type": 3
            }
          ]
        },
        "ads_service": {
          "status": 2
        }
      }
    }
  ],
  "configuration_version": "1"
}